[
  {
    "id": 1,
    "title": "Pixel Runner",
    "companyName": "Innovatech Labs",
    "image": "https://i.ibb.co/8Dtwvs94/pixel-runner-dawn-stockcake.jpg",
    "description": "This is the description for Pixel Runner 3D 76. It helps you manage your daily life and tasks efficiently.",
    "size": 178.5,
    "reviews": 349697,
    "ratingAvg": 4.6,
    "downloads": 7,
    "Mb": 120,
    "ratings": [
      {
        "name": "1 star",
        "count": 17484
      },
      {
        "name": "2 star",
        "count": 17484
      },
      {
        "name": "3 star",
        "count": 52454
      },
      {
        "name": "4 star",
        "count": 108156
      },
      {
        "name": "5 star",
        "count": 159119
      }
    ]
  },
  {
    "id": 2,
    "title": "Finance Tracker",
    "companyName": "Global Devs",
    "image": "https://i.ibb.co/VWDNCWDj/regularly-keep-track-your-expenses-260nw-2274231043.webp",
    "description": "This is the description for Finance Tracker Pro 49. It helps you manage your daily life and tasks efficiently.",
    "size": 114.7,
    "reviews": 328004,
    "ratingAvg": 3.7,
    "downloads": 5,
    "Mb": 150,
    "ratings": [
      {
        "name": "1 star",
        "count": 25777
      },
      {
        "name": "2 star",
        "count": 16400
      },
      {
        "name": "3 star",
        "count": 48777
      },
      {
        "name": "4 star",
        "count": 94848
      },
      {
        "name": "5 star",
        "count": 142202
      }
    ]
  },
  {
    "id": 3,
    "title": "Daily Recipes",
    "companyName": "SoftStream Studio",
    "image": "https://i.ibb.co/x8Kx07BK/Good-Morning-Bangkok-Salad-wordpress.webp",
    "description": "This is the description for Daily Recipes 35. It helps you manage your daily life and tasks efficiently.",
    "size": 158.3,
    "reviews": 303437,
    "ratingAvg": 4.1,
    "downloads": 48.6,
    "Mb": 190,
    "ratings": [
      {
        "name": "1 star",
        "count": 18260
      },
      {
        "name": "2 star",
        "count": 15171
      },
      {
        "name": "3 star",
        "count": 46685
      },
      {
        "name": "4 star",
        "count": 87832
      },
      {
        "name": "5 star",
        "count": 135489
      }
    ]
  },
  {
    "id": 4,
    "title": "AI Photo Editor",
    "companyName": "Apex Solutions",
    "image": "https://i.ibb.co/607kYKtx/one-click-automatic-photo-enhancement-using-Fotor-AI-photo-editor-1.jpg",
    "description": "This is the description for AI Photo Editor 88. It helps you manage your daily life and tasks efficiently.",
    "size": 65.5,
    "reviews": 331778,
    "ratingAvg": 4.9,
    "downloads": 1.2,
    "Mb": 190,
    "ratings": [
      {
        "name": "1 star",
        "count": 7921
      },
      {
        "name": "2 star",
        "count": 16588
      },
      {
        "name": "3 star",
        "count": 48983
      },
      {
        "name": "4 star",
        "count": 106419
      },
      {
        "name": "5 star",
        "count": 151867
      }
    ]
  },

  {
    "id": 5,
    "title": "Code Snippet Vault",
    "companyName": "Health Flow Inc.",
    "image": "https://i.ibb.co/xKd0vpYW/Word-Press-code-snippets-1120x630.png",
    "description": "This is the description for Code Snippet Vault 42. It helps you manage your daily life and tasks efficiently.",
    "size": 161.4,
    "reviews": 421683,
    "ratingAvg": 4.5,
    "downloads": 4,
    "Mb": 220,
    "ratings": [
      {
        "name": "1 star",
        "count": 16445
      },
      {
        "name": "2 star",
        "count": 21084
      },
      {
        "name": "3 star",
        "count": 59970
      },
      {
        "name": "4 star",
        "count": 127909
      },
      {
        "name": "5 star",
        "count": 196275
      }
    ]
  },
  {
    "id": 6,
    "title": "Virtual Yoga Studio",
    "companyName": "Innovatech Labs",
    "image": "https://i.ibb.co/LDsnYGFg/14-virtual-yoga-class-1-1-609x240.png",
    "description": "This is the description for Virtual Yoga Studio 93. It helps you manage your daily life and tasks efficiently.",
    "size": 224.2,
    "reviews": 238260,
    "ratingAvg": 4.3,
    "downloads": 7,
    "Mb": 140,
    "ratings": [
      {
        "name": "1 star",
        "count": 14041
      },
      {
        "name": "2 star",
        "count": 11913
      },
      {
        "name": "3 star",
        "count": 36186
      },
      {
        "name": "4 star",
        "count": 74586
      },
      {
        "name": "5 star",
        "count": 101534
      }
    ]
  },

  {
    "id": 7,
    "title": "Weather Now ",
    "companyName": "Apex Solutions",
    "image": "https://i.ibb.co/1tPRxGgg/images.jpg",
    "description": "This is the description for Weather Now 24/7 23. It helps you manage your daily life and tasks efficiently.",
    "size": 13.9,
    "reviews": 239276,
    "ratingAvg": 3.6,
    "downloads": 6,
    "Mb": 140,
    "ratings": [
      {
        "name": "1 star",
        "count": 21470
      },
      {
        "name": "2 star",
        "count": 11963
      },
      {
        "name": "3 star",
        "count": 34493
      },
      {
        "name": "4 star",
        "count": 68637
      },
      {
        "name": "5 star",
        "count": 102713
      }
    ]
  },
  {
    "id": 8,
    "image": "https://i.ibb.co/jvBJT87j/pngtree-illustration-keep-productive-at-home-even-when-working-from-home-in-png-image-2219878.jpg",
    "title": "Productify - Task Manager",
    "companyName": "HeroSoft",
    "description": "A modern productivity app that helps you organize tasks, set goals, and track your daily progress effortlessly.",
    "size": 54,
    "reviews": 1200,
    "ratingAvg": 4.7,
    "downloads": 1.2,
    "Mb": 121,
    "ratings": [
      { "name": "1 star", "count": 45 },
      { "name": "2 star", "count": 60 },
      { "name": "3 star", "count": 150 },
      { "name": "4 star", "count": 410 },
      { "name": "5 star", "count": 535 }
    ]
  },
  {
    "id": 9,
    "image": "https://i.ibb.co/Xfp65SCX/S9c7321edf1064f13b83189f351248a48d.webp",
    "title": "FitZone - Fitness Tracker",
    "companyName": "ActiveLab",
    "description": "Track your workouts, monitor calories, and stay motivated with real-time progress tracking and health tips.",
    "size": 70,
    "reviews": 980,
    "ratingAvg": 4.5,
    "downloads": 3.1,
    "Mb": 154,
    "ratings": [
      { "name": "1 star", "count": 80 },
      { "name": "2 star", "count": 90 },
      { "name": "3 star", "count": 120 },
      { "name": "4 star", "count": 300 },
      { "name": "5 star", "count": 390 }
    ]
  },
  {
    "id": 10,
    "image": "https://i.ibb.co/WvbbLMS9/Encrypted-Messaging-Icon.png",
    "title": "Secure Messenger",
    "companyName": "HeroSoft",
    "description": "Stay connected with friends and family with end-to-end encrypted chat, voice, and video calls.",
    "size": 62,
    "reviews": 2200,
    "ratingAvg": 4.8,
    "downloads": 10,
    "Mb": 430,
    "ratings": [
      { "name": "1 star", "count": 50 },
      { "name": "2 star", "count": 70 },
      { "name": "3 star", "count": 180 },
      { "name": "4 star", "count": 600 },
      { "name": "5 star", "count": 1300 }
    ]
  },
  {
    "id": 11,
    "image": "https://i.ibb.co/vCvjv7MV/original-e6806c2faffac2977e17f5a5489317c5.webp",
    "title": "FinPal -Tracker",
    "companyName": "MoneyMate",
    "description": "Easily manage your expenses, set monthly budgets, and visualize your spending habits with smart analytics.",
    "size": 48,
    "reviews": 860,
    "ratingAvg": 4.6,
    "downloads": 3,
    "Mb": 34,
    "ratings": [
      { "name": "1 star", "count": 40 },
      { "name": "2 star", "count": 55 },
      { "name": "3 star", "count": 100 },
      { "name": "4 star", "count": 300 },
      { "name": "5 star", "count": 365 }
    ]
  },
  {
    "id": 12,
    "image": "https://i.ibb.co/twFjmZxM/acfab37d2cdf936780d6c613096891a1-icon.png",
    "title": "PicVerse - Photo Editor",
    "companyName": "HeroSoft",
    "description": "Create stunning visuals with AI-powered filters, effects, and easy one-tap editing tools for any photo.",
    "size": 95,
    "reviews": 2000,
    "ratingAvg": 4.9,
    "downloads": 12,
    "Mb": 40,
    "ratings": [
      { "name": "1 star", "count": 35 },
      { "name": "2 star", "count": 40 },
      { "name": "3 star", "count": 90 },
      { "name": "4 star", "count": 450 },
      { "name": "5 star", "count": 1385 }
    ]
  },
  {
    "id": 13,
    "image": "https://i.ibb.co/b59TQRmy/shopwise-logo-bg.png",
    "title": "Smart Shopping App",
    "companyName": "SmartCart Ltd",
    "description": "Compare prices, track deals, and get real-time discounts from thousands of online stores in one app.",
    "size": 80,
    "reviews": 1300,
    "ratingAvg": 4.4,
    "downloads": 3,
    "Mb": 54,
    "ratings": [
      { "name": "1 star", "count": 100 },
      { "name": "2 star", "count": 120 },
      { "name": "3 star", "count": 200 },
      { "name": "4 star", "count": 420 },
      { "name": "5 star", "count": 460 }
    ]
  },
  {
    "id": 14,
    "image": "https://i.ibb.co/Z6jSTQC4/2023-08-16-64dd34d948baa.jpg",
    "title": "MusicFlow - Stream ",
    "companyName": "BeatLab",
    "description": "Listen to millions of songs, create playlists, and enjoy personalized music recommendations every day.",
    "size": 110,
    "reviews": 3100,
    "ratingAvg": 4.9,
    "downloads": 2.3,
    "Mb": 95,
    "ratings": [
      { "name": "1 star", "count": 70 },
      { "name": "2 star", "count": 85 },
      { "name": "3 star", "count": 210 },
      { "name": "4 star", "count": 700 },
      { "name": "5 star", "count": 2035 }
    ]
  },
  {
    "id": 15,
    "image": "https://i.ibb.co/1YsLJFmv/5v7n-Mw-ZRMf-Ya-Sc-Fn2-BK4p-K.jpg",
    "title": " Skill Learning App",
    "companyName": "HeroSoft",
    "description": "Learn coding, design, and business skills with video lessons, quizzes, and interactive projects.",
    "size": 77,
    "reviews": 1900,
    "ratingAvg": 4.7,
    "downloads": 7.4,
    "Mb": 56,
    "ratings": [
      { "name": "1 star", "count": 60 },
      { "name": "2 star", "count": 80 },
      { "name": "3 star", "count": 130 },
      { "name": "4 star", "count": 490 },
      { "name": "5 star", "count": 1140 }
    ]
  },
  {
    "id": 16,
    "image": "https://i.ibb.co/0y6WF9cD/unnamed.png",
    "title": "GameHub",
    "companyName": "PlaySphere",
    "description": "Discover and play trending mobile games, join gaming communities, and compete in tournaments.",
    "size": 150,
    "reviews": 2400,
    "ratingAvg": 4.6,
    "downloads": 21,
    "Mb": 120,
    "ratings": [
      { "name": "1 star", "count": 90 },
      { "name": "2 star", "count": 100 },
      { "name": "3 star", "count": 220 },
      { "name": "4 star", "count": 600 },
      { "name": "5 star", "count": 1390 }
    ]
  },
  {
    "id": 17,
    "image": "https://i.ibb.co/DHPG9LpL/yondh-SDj-Dr-BDn-OQ9bf-Fo9.jpg",
    "title": "Weatherly - Smart Forecast",
    "companyName": "CloudTech",
    "description": "Get accurate weather updates, hourly forecasts, and AI-based storm alerts in real-time.",
    "size": 55,
    "reviews": 650,
    "ratingAvg": 4.3,
    "downloads": 45,
    "Mb": 153,
    "ratings": [
      { "name": "1 star", "count": 50 },
      { "name": "2 star", "count": 60 },
      { "name": "3 star", "count": 100 },
      { "name": "4 star", "count": 210 },
      { "name": "5 star", "count": 230 }
    ]
  },
  {
    "id": 18,
    "image": "https://i.ibb.co/cK2y71P3/banner-01.jpg",
    "title": "TravelGo - Trip Planner",
    "companyName": "HeroSoft",
    "description": "Plan your trips, book hotels, and explore destinations with AI-generated travel itineraries.",
    "size": 90,
    "reviews": 1700,
    "ratingAvg": 4.8,
    "downloads": 112,
    "Mb": 123,
    "ratings": [
      { "name": "1 star", "count": 40 },
      { "name": "2 star", "count": 50 },
      { "name": "3 star", "count": 140 },
      { "name": "4 star", "count": 420 },
      { "name": "5 star", "count": 1050 }
    ]
  },
  {
    "id": 19,
    "image": "https://i.ibb.co/23dxRhWf/ebookreaders-2048px-9581.webp",
    "title": "Ebook Reader",
    "companyName": "BookVerse",
    "description": "Read, highlight, and save your favorite ebooks with a personalized reading experience and note sync.",
    "size": 68,
    "reviews": 890,
    "ratingAvg": 4.5,
    "downloads": 6,
    "Mb": 140,
    "ratings": [
      { "name": "1 star", "count": 55 },
      { "name": "2 star", "count": 70 },
      { "name": "3 star", "count": 130 },
      { "name": "4 star", "count": 260 },
      { "name": "5 star", "count": 375 }
    ]
  },
  {
    "id": 20,
    "image": "https://i.ibb.co/0jRZ0BY0/One-on-One-Medicare-1.png",
    "title": "MediCare - Health Assistant",
    "companyName": "HealthBridge",
    "description": "Get medical reminders, track symptoms, and consult doctors online using your smart health assistant.",
    "size": 85,
    "reviews": 2100,
    "ratingAvg": 4.9,
    "downloads": 15,
    "Mb": 150,
    "ratings": [
      { "name": "1 star", "count": 40 },
      { "name": "2 star", "count": 55 },
      { "name": "3 star", "count": 120 },
      { "name": "4 star", "count": 480 },
      { "name": "5 star", "count": 1405 }
    ]
  }
]
